qsd/__init__.py
qsd/data_processing/__init__.py
qsd/data_processing/postproc.py
qsd/data_processing/preproc.py
qsd/data_processing/readcomsol.py
qsd/data_processing/setparams.py
qsd/electromagnetics/__init__.py
qsd/electromagnetics/cpw.py
qsd/ssh_control/__init__.py
qsd/ssh_control/sshcommand.py
qsd-0.1.2.dist-info/METADATA
qsd-0.1.2.dist-info/WHEEL
qsd-0.1.2.dist-info/top_level.txt
qsd-0.1.2.dist-info/RECORD
