Metadata-Version: 2.1
Name: qsd
Version: 0.1.2
Summary: UNKNOWN
Home-page: UNKNOWN
Author: Gareth Sion Jones
Author-email: garethsion@googlemail.com
License: UNKNOWN
Project-URL: Documentation, https://qsd.readthedocs.io/
Project-URL: Source, https://github.com/garethsion/qsd.git
Platform: UNKNOWN
Requires-Python: >3.4.0
Requires-Dist: numpy
Requires-Dist: scipy
